{
    "totalItems": 88,
    "totalGroups": 70,
    "offset": 0,
    "sort": "airtime_default",
    "navigators": [
        {
            "id": "cluster",
            "name": "Cluster",
            "entries": [
                {
                    "id": "tv",
                    "name": "TV Sendung",
                    "size": 23
                },
                {
                    "id": "vodSeries",
                    "name": "Serie",
                    "size": 65
                }
            ]
        }
    ],
    "results": []
}
